CHANGELOG.txt
COPYING.txt
MANIFEST.in
README.rst
setup.cfg
setup.py
/home/gv10-debian/Workspace/pyNFFT/pynfft/nfft.c
/home/gv10-debian/Workspace/pyNFFT/pynfft/solver.c
/home/gv10-debian/Workspace/pyNFFT/pynfft/util.c
doc/Makefile
doc/source/api.rst
doc/source/conf.py
doc/source/index.rst
doc/source/tutorial.rst
doc/source/api/nfft.rst
doc/source/api/solver.rst
doc/source/api/util.rst
pyNFFT.egg-info/PKG-INFO
pyNFFT.egg-info/SOURCES.txt
pyNFFT.egg-info/dependency_links.txt
pyNFFT.egg-info/top_level.txt
pynfft/__init__.py
pynfft/cnfft3.pxd
pynfft/cnfft3util.pxd
pynfft/nfft.c
pynfft/nfft.pxd
pynfft/nfft.pyx
pynfft/solver.c
pynfft/solver.pxd
pynfft/solver.pyx
pynfft/util.c
pynfft/util.pyx
pynfft/version.py
pynfft/tests/__init__.py
pynfft/tests/test_nfft.py