Metadata-Version: 1.1
Name: pyNFFT
Version: 1.3.2
Summary: A pythonic wrapper around NFFT
Home-page: https://github.com/ghisvail/pyNFFT.git
Author: Ghislain Vaillant
Author-email: ghisvail@gmail.com
License: UNKNOWN
Platform: Linux
Platform: Unix
Classifier: Programming Language :: Cython
Classifier: Programming Language :: Python
Classifier: Programming Language :: Python :: 2
Classifier: Programming Language :: Python :: 2.6
Classifier: Programming Language :: Python :: 2.7
Classifier: Programming Language :: Python :: 3
Classifier: Programming Language :: Python :: 3.2
Classifier: Programming Language :: Python :: 3.3
Classifier: Programming Language :: Python :: 3.4
Classifier: Development Status :: 4 - Beta
Classifier: License :: OSI Approved :: GNU General Public License v3 or later (GPLv3+)
Classifier: Operating System :: POSIX :: Linux
Classifier: Intended Audience :: Developers
Classifier: Intended Audience :: Science/Research
Classifier: Topic :: Scientific/Engineering
Classifier: Topic :: Scientific/Engineering :: Mathematics
Classifier: Topic :: Multimedia :: Sound/Audio :: Analysis
